{
"type": "FeatureCollection",
"name": "mean valuesZhuang",
"crs": { "type": "name", "properties": { "name": "urn:ogc:def:crs:OGC:1.3:CRS84" } },
"features": [
{ "type": "Feature", "properties": { "MEAN_X": 115.36333478260872, "MEAN_Y": 35.014736500434786 }, "geometry": { "type": "Point", "coordinates": [ 115.363334782608717, 35.014736500434786 ] } }
]
}
